rebel_forge/__init__.py
rebel_forge/_service.py
rebel_forge/cli.py
rebel_forge/credential_cache.py
rebel_forge/device.py
rebel_forge/env.py
rebel_forge/onboarding.py
rebel_forge/rebel_forge.py
rebel_forge/remote.py
rebel_forge/sample.py
rebel_forge-0.11.0.dist-info/licenses/LICENSE
rebel_forge-0.11.0.dist-info/METADATA
rebel_forge-0.11.0.dist-info/WHEEL
rebel_forge-0.11.0.dist-info/entry_points.txt
rebel_forge-0.11.0.dist-info/top_level.txt
rebel_forge-0.11.0.dist-info/RECORD
