Metadata-Version: 2.4
Name: rebel-forge
Version: 0.11.0
Summary: Config-driven QLoRA/LoRA fine-tuning toolkit for Rebel Forge
Author: Rebel AI
License-Expression: LicenseRef-Proprietary
Keywords: qlora,lora,fine-tuning,transformers,rebel
Requires-Python: >=3.9
License-File: LICENSE
Requires-Dist: datasets<5.0.0,>=3.0.1
Requires-Dist: fsspec[http]<2026.0.0,>=2023.1.0
Requires-Dist: numpy<3.0.0,>=1.26.0
Requires-Dist: accelerate<0.31.0,>=0.30.0
Requires-Dist: peft<0.18.0,>=0.12.0
Requires-Dist: sentencepiece>=0.2.0
Requires-Dist: transformers<4.41.0,>=4.38.0
Requires-Dist: importlib_metadata>=7.0.0; python_version < "3.10"
Requires-Dist: PyYAML<7.0.0,>=6.0.0
Requires-Dist: keyring<26.0.0,>=24.3.0
Provides-Extra: cpu
Requires-Dist: torch<2.3.0,>=2.1.0; extra == "cpu"
Provides-Extra: cuda
Requires-Dist: torch==2.2.2; extra == "cuda"
Requires-Dist: bitsandbytes==0.43.3; extra == "cuda"
Provides-Extra: dev
Requires-Dist: build>=1.3.0; extra == "dev"
Requires-Dist: twine>=5.1.1; extra == "dev"
Dynamic: license-file
